Metadata-Version: 2.4
Name: x_4357_make_py_venv_x
Version: 0.20.17
Summary: Interpreter furnace that installs Python versions, forges named virtualenvs, and syncs tooling manifests for every orchestrator stage.
Author-email: "RRGM (Software Tech Lead, Primus Pilus Night Watch AI Corp.)" <foo@bar.com>
Requires-Python: >=3.8
